{
  "title": [
    "/FaceSet/cle-1.png",
    "/FaceSet/cle-11.png",
    "/Sound/Bruit.opus",
    "/Sound/Entree_.opus",
    "/Sound/Echap_.opus"
  ],
  "0005": [
    "*/Battle/ronces.png",
    "/Battle/money.png",
    "/Battle/get .png",
    "/Battle/fumee.png",
    "*/CharSet/epine.png",
    "/CharSet/etoile.png",
    "/CharSet/effetSKi.png",
    "/CharSet/radioactif-effect.png",
    "/CharSet/Cosplay effect.png",
    "/CharSet/radiateur-effect-2.png",
    "/CharSet/EffetChanceCorrection.png",
    "/CharSet/Cougar et fou.png",
    "/CharSet/miel.png",
    "/CharSet/racaille.png",
    "/CharSet/effect souris.png",
    "/CharSet/cougar effect.png",
    "/CharSet/visse.png",
    "/CharSet/commere-effect.png",
    "/CharSet/chewgumeffect.png",
    "/CharSet/Cerise-1.png",
    "/CharSet/boite effet.png",
    "/CharSet/soldes.png",
    "/CharSet/fideledutemple.png",
    "/CharSet/calendrier+crepage.png",
    "/CharSet/calendrieranimation.png",
    "/CharSet/perroquet .png",
    "/CharSet/radiateur-effet.png",
    "*/Picture/Tache1.png",
    "/Picture/Tache2.png",
    "/Picture/Tache3.png",
    "/Picture/Tache4.png",
    "/Picture/Tache5.png",
    "/Picture/Tache6.png",
    "/Picture/Tache7.png",
    "/Picture/Tache8.png",
    "/Picture/Tache9.png",
    "/Picture/Tache10.png",
    "/Picture/Mange6.png",
    "/Picture/beurk4.png",
    "/Picture/beurk5.png",
    "/Picture/beurk.png",
    "/Picture/beurk2.png",
    "/Picture/beurk3.png",
    "/Picture/vision .png",
    "/Picture/EffetChanceApparition1.png",
    "/Picture/EffetChanceApparition2.png",
    "*/Sound/effect1.opus",
    "/Sound/0127.opus",
    "/Sound/Argent.opus",
    "/Sound/effect2.opus",
    "/Sound/Valve.opus",
    "/Sound/Nyahahaha.opus",
    "/Sound/Sylvain.opus",
    "/Sound/Pas-eau.opus",
    "/Sound/Splouch.opus",
    "/Sound/Pshiouou.opus",
    "/Sound/Oh_yes.opus",
    "/Sound/Miel.opus",
    "/Sound/179008__smartwentcody__aerosol-can-spray.opus",
    "/Sound/Drill-SoundBible.com-1370234511.opus",
    "/Sound/Dechire.opus",
    "/Sound/Rire.opus",
    "/Sound/Guming2.opus",
    "/Sound/Guming3.opus",
    "/Sound/Guming.opus",
    "/Music/Nuitdefolie.opus",
    "/Sound/Abstrait1.opus",
    "/Sound/Etoile.opus"
  ],
  "0006": [
    "*/Picture/Mange1.png",
    "/Picture/Mange2.png",
    "/Picture/Mange3.png",
    "/Picture/Mange4.png",
    "/Picture/Mange5.png",
    "*/Map0236.lmu",
    "/ChipSet/orbes .png",
    "/CharSet/illumination (3).png",
    "*/Map0237.lmu",
    "/ChipSet/semaphore-2.png",
    "*/Panorama/Nexus.png",
    "/CharSet/fleurspatientes.png",
    "/CharSet/animaux.png",
    "/Panorama/NexusHiver.png",
    "/Panorama/Nexus-Rose.png",
    "/Picture/papillon-vol.png",
    "/Picture/papillon -4-vol.png",
    "/Picture/papillon -3-vol.png",
    "/Picture/papillon -2-vol.png",
    "/Panorama/Nexusinondation-2.png",
    "/Picture/Ciel Bleu.png"
  ],
  "0022": [
    "/Picture/Mamie.png",
    "/Picture/Mamie1.png",
    "/Picture/Mamie2.png",
    "/Picture/Mamie3.png",
    "/Picture/Mamie4.png",
    "/Picture/Mamie5.png",
    "/Picture/Mamie6.png",
    "/Picture/Mamie7.png",
    "/Picture/Mamie8.png",
    "/Picture/Mamie9.png",
    "/Picture/Mamie10.png"
  ],
  "0025": [
    "/Map0084.lmu",
    "/Panorama/Poissoncarre.png",
    "/ChipSet/naissance .png",
    "/CharSet/Torched.png",
    "/CharSet/chaudron .png"
  ],
  "0030": [
    "/Panorama/Usine2.png",
    "/Panorama/Usine3.png",
    "/Panorama/Usine4.png",
    "/Panorama/Usine5.png"
  ],
  "0067": [
    "/Map0108.lmu",
    "/Panorama/Sylvain.png",
    "/ChipSet/temple.png"
  ],
  "0068": [
    { "x": 74, "y": 90, "files": [
      "/Map0069.lmu",
      "/ChipSet/mondetenebre.png",
      "/CharSet/tenebreobjets.png",
      "/CharSet/GolemWorldPerso.png",
      "/ChipSet/mondetenebreAUTOMNE.png"
    ]}
  ],
  "0070": [
    "/Picture/Soiree-5.png",
    "/Panorama/Mistillite.png",
    "/Panorama/Figues.png",
    "/Picture/Fleur7.png",
    "/Picture/Fleur8.png",
    "/Picture/Fleur9.png",
    "/Picture/Fleur10.png",
    "/Picture/Fleur11.png",
    "/Picture/Fleur1.png",
    "/Picture/Bougliglou8.png",
    "/Picture/Bougliglou9.png",
    "/Picture/Bougliglou10.png",
    "/Picture/Bougliglou12.png",
    "/Picture/Bougliglou11.png",
    "/Picture/Bougliglou13.png",
    "/Picture/Bougliglou14.png",
    { "delay": 400, "slow": true, "files": [
      "/Music/Praline.opus",
      "/Music/PianoaiP.opus",
      "/Music/Pluijolijoli.opus",
      "/Music/Mamy-Rave.opus",
      "/Music/LeGrobegonia.opus",
      "/Music/Neunoeil.opus",
      "/Music/Gold.opus",
      "/Music/Infos.opus"
    ]}
  ],
  "0071": [
    "/Panorama/Chateau2.png",
    "/Panorama/Chateau5.png",
    "/Panorama/Chateau3.png"
  ],
  "0064/0077": [
    "/Map0141.lmu",
    "/ChipSet/melasse.png",
    "/CharSet/archeologue .png"
  ],
  "0084": [
    "/Map0085.lmu",
    "/Panorama/ete.png"
  ],
  "0089": [
    "/Map0200.lmu",
    "/ChipSet/pluie+epacse2.png"
  ],
  "0103": [
    "/Sound/Bouton.opus",
    "/Picture/projecteur-1.png",
    "/Picture/projecteur-2.png",
    "/Picture/projecteur-3.png",
    "/Picture/projecteur-4.png"
  ],
  "0108": [
    "/Panorama/Koala.png",
    "/Panorama/Herisson.png",
    "/Panorama/Ornithorynque.png"
  ],
  "0112": [
    "/Map0114.lmu",
    "/Panorama/fond bulle.png",
    "/ChipSet/MondeCrazyMazeEtBulle.png",
    "/CharSet/SaisonAlexandre-2.png",
    "/CharSet/MondeCrazyMazeEtBullePerso.png",
    "/CharSet/mondehopitalperso-2.png",
    "/CharSet/GolemWorldPerso.png",
    "/ChipSet/MondeCrazyMazeEtBulleAUTOMNE.png"
  ],
  "0114": [
    "/Map0102.lmu",
    "/ChipSet/balcon.png"
  ],
  "0139": [
    "/Map0192.lmu",
    "/ChipSet/MondeZooZone1.png",
    "/CharSet/brossedentsauvagettes.png",
    "/CharSet/ZooBebete.png",
    "/CharSet/MondeZooZone3Girafes2.png",
    "/CharSet/MondeZooPerso3.png",
    "/CharSet/animaux monde zoo.png",
    "/CharSet/Pnjs_zoo1.png"
  ],
  "0140": [
    "/Map0159.lmu",
    "/Panorama/pate.png",
    "/ChipSet/centrale.png"
  ],
  "0141": [
    "*/Map0064.lmu",
    "/Panorama/bouton fond.png",
    "/ChipSet/monde glauque.png",
    "*/Map0077.lmu",
    "/Panorama/Pastel.png",
    "/ChipSet/abstrait.png",
    "/CharSet/machine.png",
    "/CharSet/abstrait perso (1).png"
  ],
  "0158": [
    "/Sound/Portation .opus",
    "/Map0160.lmu",
    "/ChipSet/nurseeuh.png",
    "/CharSet/chasers.png",
    "/CharSet/embryon.png"
  ],
  "0159": [
    "*/Map0140.lmu",
    "/ChipSet/artichauts .png",
    "/CharSet/chaudron .png",
    "*/Map0158.lmu",
    "/Panorama/Chaiselongue.png",
    "*/Map0170.lmu",
    "/ChipSet/geyser.png",
    "/CharSet/accordeon-effect.png"
  ],
  "0168": [
    "/Picture/chezroxaneombre3TV.png",
    "/Picture/chezroxaneombre2TV.png",
    "/Picture/chezroxaneombre1TV.png",
    "/Picture/ombre-tv-3.png",
    "/Picture/ombre-tv-2.png",
    "/Picture/ombre-tv-1.png",
    "/Picture/chezroxaneombre3.png",
    "/Picture/chezroxaneombre2.png",
    "/Picture/chezroxaneombre1.png"
  ],
  "0169": [
    "/Map0171.lmu",
    "/Panorama/fonplui2.png",
    "/ChipSet/bobos.png",
    "/CharSet/linge.png"
  ],
  "0170": [
    "/Map0157.lmu",
    "/Panorama/tapis;.png",
    "/ChipSet/brosseadents.png",
    "/CharSet/brossedentsauvagettes.png",
    "/CharSet/brossedentsauvagettes-2.png",
    "/CharSet/brossedentsauvagettes-3.png",
    "/CharSet/pshiit.png"
  ],
  "0172/0174": [
    "/ChipSet/campagne hiver.png",
    "/ChipSet/campagne printemps  .png",
    "/ChipSet/campagne .png",
    "/ChipSet/campagne automne.png"
  ],
  "0172": [
    "/Map0174.lmu",
    "/CharSet/champs perso.png"
  ],
  "0181": [
    "*/Picture/wait3.png",
    "/Picture/wait2.png",
    "/Picture/wait.png",
    "/Picture/wait4.png",
    "*/Picture/photoski.png",
    "/Picture/photonoel.png",
    "/Picture/ImageLivrePhotoAlexImg3.png",
    "/Picture/ImageLivrePhotoAlexImg2Tache.png",
    "/Picture/ImageLivrePhotoAlexImg1.png",
    "/Picture/Photo-2.png",
    "/Picture/Photo-1.png",
    "/Picture/album photo.png",
    "*/Map0005.lmu",
    "/Panorama/ciel jour reve.png",
    "/ChipSet/balcon-reve.png",
    "/CharSet/visiteurs .png",
    "/CharSet/evenements .png",
    "/Picture/panneau-bus-balcon.png",
    "/Picture/ombres-arbres-1 V.2.png",
    "/Picture/ombres-arbres-2 V.2.png",
    "/Picture/ombres-arbres-3 V.2.png"
  ],
  "0184": [
    { "delay": 1000, "slow": true, "files": [
      "*/Picture/Tv1.png",
      "/Picture/Tv2.png",
      "*/Panorama/Noirfond.png",
      "/Picture/Mange6.png",
      "/Picture/Alexandrine;.png",
      "/Picture/PianoaiP-1.png",
      "/Picture/PianoaiP-3.png",
      "/Picture/PianoaiP-2.png",
      "/Picture/PianoaiP-4.png",
      "/Picture/PianoaiP-5.png",
      "/Picture/PianoaiP-6.png",
      "/Picture/Soiree-1.png",
      "/Panorama/CavernOpop.png",
      "/Picture/Soiree-2.png",
      "/Picture/Soiree-3.png",
      "/Picture/Oulala1.png",
      "/Picture/Oulala2.png",
      "/Picture/Oulala3.png",
      "/Picture/Cafe1.png",
      "/Picture/Cafe2.png",
      "/Picture/Fleur12.png",
      "/Picture/Fleur2.png",
      "/Picture/Fleur3.png",
      "/Picture/Fleur4.png",
      "/Picture/Fleur5.png",
      "/Picture/Fleur6.png",
      "/Picture/Gold.png",
      "/Picture/ChaineTVAlex.png",
      "/Picture/Fondinfos.png",
      "/Picture/Bougliglou1.png",
      "/Picture/Bougliglou2.png",
      "/Picture/Bougliglou3.png",
      "/Picture/Bougliglou4.png",
      "/Picture/Bougliglou5.png",
      "/Picture/Bougliglou6.png",
      "/Picture/Bougliglou7.png",
      "/Music/Soiree.opus"
    ]}
  ],
  "0186": [
    "/Music/Ambiance+Wouhouhou.opus"
  ],
  "0187": [
    "/Music/Aaaaagnes.opus",
    "/Music/Guitare.opus"
  ],
  "0196": [
    "/Panorama/bac-grand-1.png",
    "/Panorama/bac-grand-2.png"
  ],
  "0201": [
    "/Picture/RegleSequoia2.png",
    "/Picture/RegleSequoia.png",
    "/Picture/stoproue.png",
    "/Picture/fortune .png"
  ],
  "0203": [
    "*/Picture/planete-1.png",
    "/Picture/planete-2.png",
    "/Picture/planete-3.png",
    "/Picture/planete-4.png",
    "/Picture/planete-5.png",
    "/Picture/planete-6.png",
    "/Picture/planete-7.png",
    "/Picture/planete-8.png",
    "*/Map0112.lmu",
    "/Panorama/pendule .png",
    "/ChipSet/flou.png",
    "/CharSet/flou perso.png",
    "/CharSet/Alexandra .png"
  ],
  "0205": [
    "/Map0208.lmu",
    "/ChipSet/MondeGlace(Ski).png",
    "/CharSet/MondeGlacePerso(Ski).png"
  ],
  "0212": [
    "/Picture/astro-etageFINBas.png",
    "/Picture/astro-etageFINHaut.png"
  ],
  "0223": [
    "/Map0175.lmu",
    "/ChipSet/Orange.png"
  ],
  "0237": [
    "/Map0238.lmu"
  ],
  "0238": [
    "/Map0239.lmu"
  ],
  "0239": [
    "/Map0240.lmu"
  ],
  "0240": [
    "/Map0241.lmu"
  ],
  "0241": [
    "/Map0243.lmu",
    "/Panorama/Ciel Bleu.png",
    "/CharSet/somewhere.png"
  ],
  "0243": [
    "/Map0068.lmu",
    "/Panorama/Fondrerere.png",
    "/ChipSet/ronce.png",
    "/CharSet/bonus.png"
  ],
  "0247": [
    "/Map0140.lmu",
    "/ChipSet/artichauts .png"
  ]
}